chrispy/__init__.py
chrispy-0.2.0.dist-info/LICENSE
chrispy-0.2.0.dist-info/METADATA
chrispy-0.2.0.dist-info/WHEEL
chrispy-0.2.0.dist-info/RECORD
